dagster_contrib_modal/__init__.py
dagster_contrib_modal/resources.py
dagster_contrib_modal-0.0.2.dist-info/METADATA
dagster_contrib_modal-0.0.2.dist-info/WHEEL
dagster_contrib_modal-0.0.2.dist-info/top_level.txt
dagster_contrib_modal-0.0.2.dist-info/RECORD
