Metadata-Version: 2.1
Name: dagster-contrib-modal
Version: 0.0.2
Summary: Dagster integration with Modal
Requires-Python: >=3.8
Requires-Dist: dagster-pipes>=1.7.0
Requires-Dist: dagster>=1.7.0
Requires-Dist: modal>=0.64.163
